odoo/addons/stock_available_to_promise_release_delivery/README.rst
odoo/addons/stock_available_to_promise_release_delivery/__init__.py
odoo/addons/stock_available_to_promise_release_delivery/__manifest__.py
odoo/addons/stock_available_to_promise_release_delivery/i18n/it.po
odoo/addons/stock_available_to_promise_release_delivery/i18n/stock_available_to_promise_release_delivery.pot
odoo/addons/stock_available_to_promise_release_delivery/models/__init__.py
odoo/addons/stock_available_to_promise_release_delivery/models/stock_picking.py
odoo/addons/stock_available_to_promise_release_delivery/readme/CONTRIBUTORS.md
odoo/addons/stock_available_to_promise_release_delivery/readme/DESCRIPTION.md
odoo/addons/stock_available_to_promise_release_delivery/static/description/icon.png
odoo/addons/stock_available_to_promise_release_delivery/static/description/index.html
odoo/addons/stock_available_to_promise_release_delivery/tests/__init__.py
odoo/addons/stock_available_to_promise_release_delivery/tests/common.py
odoo/addons/stock_available_to_promise_release_delivery/tests/test_update_picking_carrier.py
odoo_addon_stock_available_to_promise_release_delivery-18.0.1.0.1.1.dist-info/METADATA
odoo_addon_stock_available_to_promise_release_delivery-18.0.1.0.1.1.dist-info/WHEEL
odoo_addon_stock_available_to_promise_release_delivery-18.0.1.0.1.1.dist-info/top_level.txt
odoo_addon_stock_available_to_promise_release_delivery-18.0.1.0.1.1.dist-info/RECORD
