Metadata-Version: 2.1
Name: odoo-addon-stock_available_to_promise_release_delivery
Version: 18.0.1.0.1.1
Requires-Python: >=3.10
Requires-Dist: odoo-addon-stock_available_to_promise_release==18.0.*
Requires-Dist: odoo==18.0.*
Summary: Glue module between release mechanism and delivery.
Home-page: https://github.com/OCA/stock-logistics-reservation
License: LGPL-3
Author: Camptocamp, BCIM, Odoo Community Association (OCA)
Author-email: support@odoo-community.org
Classifier: Programming Language :: Python
Classifier: Framework :: Odoo
Classifier: Framework :: Odoo :: 18.0
Classifier: License :: OSI Approved :: GNU Lesser General Public License v3 (LGPLv3)
